{
  "2026-07-25": {
    "1": "https://square.link/u/eCJPMZJC",
    "2": "https://square.link/u/NuApDcez",
    "3": "https://square.link/u/FLTvJjNU",
    "4": "https://square.link/u/OrJjyROA",
    "5": "https://square.link/u/smi8pGHI",
    "6": "https://square.link/u/dKNZBPjk",
    "7": "https://square.link/u/chnD8Fz2",
    "8": "https://square.link/u/WxnnAMjq",
    "9": "https://square.link/u/wPMLnv5M",
    "10": "https://square.link/u/VPB61Cne"
  },
  "2026-08-01": {
    "1": "https://square.link/u/Poh7gGcN",
    "2": "https://square.link/u/Rcnghe7c",
    "3": "https://square.link/u/DILF9GPT",
    "4": "https://square.link/u/EcoDGSlQ",
    "5": "https://square.link/u/pbA9afPd",
    "6": "https://square.link/u/4iqeCC7L",
    "7": "https://square.link/u/Mp6mJ8xM",
    "8": "https://square.link/u/zZCL98om",
    "9": "https://square.link/u/QvbHiSoE",
    "10": "https://square.link/u/dKtiNogH"
  },
  "2026-08-08": {
    "1": "https://square.link/u/puo9RsNv",
    "2": "https://square.link/u/uPyPDhzj",
    "3": "https://square.link/u/llF1rM4Y",
    "4": "https://square.link/u/a6pHwmzF",
    "5": "https://square.link/u/evD8FDSn",
    "6": "https://square.link/u/Ew9VbxEv",
    "7": "https://square.link/u/Kp9g7NxI",
    "8": "https://square.link/u/f3vAJsa9",
    "9": "https://square.link/u/8pCeq8gN",
    "10": "https://square.link/u/v9lLCZXl"
  },
  "2026-08-15": {
    "1": "https://square.link/u/rm9Sm5rl",
    "2": "https://square.link/u/xXL1ptzn",
    "3": "https://square.link/u/DwN4SZvK",
    "4": "https://square.link/u/v7OZ2y7W",
    "5": "https://square.link/u/OoIObCHa",
    "6": "https://square.link/u/fqdlPFHK",
    "7": "https://square.link/u/yTfD57yg",
    "8": "https://square.link/u/mSZQcDVj",
    "9": "https://square.link/u/JWizObhB",
    "10": "https://square.link/u/0ctB3Eqo"
  },
  "2026-08-22": {
    "1": "https://square.link/u/YCJC5otD",
    "2": "https://square.link/u/0N8xBhKn",
    "3": "https://square.link/u/cqrBIbo9",
    "4": "https://square.link/u/MYnmDnr1",
    "5": "https://square.link/u/FAYBZZNy",
    "6": "https://square.link/u/WSBGyCvc",
    "7": "https://square.link/u/B3kIstF4",
    "8": "https://square.link/u/dqWxkcTf",
    "9": "https://square.link/u/GjNUpdGX",
    "10": "https://square.link/u/yDChz7bK"
  },
  "2026-08-29": {
    "1": "https://square.link/u/J31Fp1v8",
    "2": "https://square.link/u/Qnumdk44",
    "3": "https://square.link/u/LrN2BHIE",
    "4": "https://square.link/u/zPIC56ZK",
    "5": "https://square.link/u/YUfEwMth",
    "6": "https://square.link/u/nYLh5Zz3",
    "7": "https://square.link/u/RM7EEzY9",
    "8": "https://square.link/u/FpwzHOLb",
    "9": "https://square.link/u/ml8zW3Ce",
    "10": "https://square.link/u/iJUnF7Dp"
  },
  "2026-09-05": {
    "1": "https://square.link/u/JgC82hJD",
    "2": "https://square.link/u/3ajFfbF7",
    "3": "https://square.link/u/fIQHNgBp",
    "4": "https://square.link/u/xQZ0dDqi",
    "5": "https://square.link/u/EAPdrs4o",
    "6": "https://square.link/u/tzj5qJKx",
    "7": "https://square.link/u/AIReUTtb",
    "8": "https://square.link/u/lHsBfKOU",
    "9": "https://square.link/u/Gd6NBCyE",
    "10": "https://square.link/u/hStVZqkr"
  },
  "2026-09-12": {
    "1": "https://square.link/u/kdBIemPA",
    "2": "https://square.link/u/KjbOB73u",
    "3": "https://square.link/u/SOVRYi4b",
    "4": "https://square.link/u/6bDUqGgY",
    "5": "https://square.link/u/XLyCJaSR",
    "6": "https://square.link/u/w3tnzZP0",
    "7": "https://square.link/u/ahVMqocl",
    "8": "https://square.link/u/eZPApoGm",
    "9": "https://square.link/u/MDnu0xlt",
    "10": "https://square.link/u/yNSoRxjl"
  },
  "2026-09-19": {
    "1": "https://square.link/u/1Q1ezmlY",
    "2": "https://square.link/u/7aWw3M64",
    "3": "https://square.link/u/RYsD3yIh",
    "4": "https://square.link/u/ygWDyDNl",
    "5": "https://square.link/u/ziPG0cOb",
    "6": "https://square.link/u/pfrR8bUA",
    "7": "https://square.link/u/D3hEZspf",
    "8": "https://square.link/u/osQIemLe",
    "9": "https://square.link/u/JypEQLLg",
    "10": "https://square.link/u/fxky0fEZ"
  },
  "2026-09-26": {
    "1": "https://square.link/u/JzAvF5T7",
    "2": "https://square.link/u/ksTZ4Oq0",
    "3": "https://square.link/u/Rn0h6PJR",
    "4": "https://square.link/u/gALPiClX",
    "5": "https://square.link/u/y7TCWiPH",
    "6": "https://square.link/u/aNaHzcp0",
    "7": "https://square.link/u/OhiEbq4g",
    "8": "https://square.link/u/Jppk0yAg",
    "9": "https://square.link/u/zjKH6aUy",
    "10": "https://square.link/u/tXvj1J5k"
  },
  "2026-10-03": {
    "1": "https://square.link/u/RXG4W7nx",
    "2": "https://square.link/u/dKMr0M3X",
    "3": "https://square.link/u/wFLdg9Vs",
    "4": "https://square.link/u/DZXpgsXc",
    "5": "https://square.link/u/zTOnC5ci",
    "6": "https://square.link/u/rO0s428U",
    "7": "https://square.link/u/Mkg8xkNu",
    "8": "https://square.link/u/tfQEab1N",
    "9": "https://square.link/u/j3ox05ar",
    "10": "https://square.link/u/p2irLfsz"
  },
  "2026-10-10": {
    "1": "https://square.link/u/5G6o5PMK",
    "2": "https://square.link/u/ZPqdez5h",
    "3": "https://square.link/u/qJOEcdGu",
    "4": "https://square.link/u/t9cUMc2o",
    "5": "https://square.link/u/wCADmWbP",
    "6": "https://square.link/u/AOz1EyK5",
    "7": "https://square.link/u/jXT3vOKU",
    "8": "https://square.link/u/ju7Zpjmd",
    "9": "https://square.link/u/0Mvxb6Kr",
    "10": "https://square.link/u/ftOjVNYh"
  },
  "2026-10-17": {
    "1": "https://square.link/u/cyYa9ndj",
    "2": "https://square.link/u/5x7375O9",
    "3": "https://square.link/u/9fesBGaX",
    "4": "https://square.link/u/VlwGhvkg",
    "5": "https://square.link/u/nuQtHuSP",
    "6": "https://square.link/u/8NXt4N0y",
    "7": "https://square.link/u/aRxqaVDo",
    "8": "https://square.link/u/TkwK1qut",
    "9": "https://square.link/u/1iR0CRIN",
    "10": "https://square.link/u/yEIYg8XH"
  },
  "2026-10-24": {
    "1": "https://square.link/u/2GJEQuCg",
    "2": "https://square.link/u/ksscbMn8",
    "3": "https://square.link/u/f2TcBCdL",
    "4": "https://square.link/u/ETzIYS4E",
    "5": "https://square.link/u/XGZCxNgd",
    "6": "https://square.link/u/Xa6oAHrO",
    "7": "https://square.link/u/yMOOzjXc",
    "8": "https://square.link/u/Z3kEshRQ",
    "9": "https://square.link/u/lgRLnNX1",
    "10": "https://square.link/u/pvFYlayN"
  },
  "2026-10-31": {
    "1": "https://square.link/u/uN4hIXcz",
    "2": "https://square.link/u/2XVngF00",
    "3": "https://square.link/u/poPdQZlD",
    "4": "https://square.link/u/0MycGFRW",
    "5": "https://square.link/u/Z9tTHxpR",
    "6": "https://square.link/u/oKgkpRcP",
    "7": "https://square.link/u/Is8oAKaD",
    "8": "https://square.link/u/6i94yf57",
    "9": "https://square.link/u/aoFaVGiG",
    "10": "https://square.link/u/NLTA424r"
  },
  "2026-11-07": {
    "1": "https://square.link/u/Wf44AAhF",
    "2": "https://square.link/u/UXUfU9PU",
    "3": "https://square.link/u/bRaP2Maq",
    "4": "https://square.link/u/U2OAxqzK",
    "5": "https://square.link/u/1bX7MTtM",
    "6": "https://square.link/u/iUWi6hpF",
    "7": "https://square.link/u/I0QqmFTk",
    "8": "https://square.link/u/EzHJOK3l",
    "9": "https://square.link/u/68clagxY",
    "10": "https://square.link/u/rpmPvily"
  },
  "2026-11-14": {
    "1": "https://square.link/u/aEiqliQt",
    "2": "https://square.link/u/NxmIBCUx",
    "3": "https://square.link/u/q90ft8OJ",
    "4": "https://square.link/u/bzsuxp6u",
    "5": "https://square.link/u/WEL2S0Pz",
    "6": "https://square.link/u/qLBWnDws",
    "7": "https://square.link/u/qnceMTxY",
    "8": "https://square.link/u/bNGcNHWd",
    "9": "https://square.link/u/FeO4VoYZ",
    "10": "https://square.link/u/WvDq0ltu"
  },
  "2026-11-21": {
    "1": "https://square.link/u/Hfe08Wm4",
    "2": "https://square.link/u/WXfjNLxN",
    "3": "https://square.link/u/BxeCS1sb",
    "4": "https://square.link/u/dwt1Dt8J",
    "5": "https://square.link/u/ZXCtzjyr",
    "6": "https://square.link/u/DGI5NCCO",
    "7": "https://square.link/u/jMFFEhe4",
    "8": "https://square.link/u/ffjLUbsZ",
    "9": "https://square.link/u/4h1HuHgn",
    "10": "https://square.link/u/IkaJ5ERu"
  },
  "2026-11-28": {
    "1": "https://square.link/u/Vx303QsX",
    "2": "https://square.link/u/XxUEOdac",
    "3": "https://square.link/u/t55SpDRI",
    "4": "https://square.link/u/TAtxSuL3",
    "5": "https://square.link/u/f0s7XKbR",
    "6": "https://square.link/u/XC3u9N0l",
    "7": "https://square.link/u/XyzzEzgt",
    "8": "https://square.link/u/ku7IFz6V",
    "9": "https://square.link/u/pGLsbb2R",
    "10": "https://square.link/u/Uv7kDN1g"
  },
  "2026-12-05": {
    "1": "https://square.link/u/PNNi70A0",
    "2": "https://square.link/u/t79Bgr7k",
    "3": "https://square.link/u/qOlRaKmI",
    "4": "https://square.link/u/GxScWauB",
    "5": "https://square.link/u/RNBqTao3",
    "6": "https://square.link/u/D1zZrMGR",
    "7": "https://square.link/u/ekqzJiTX",
    "8": "https://square.link/u/WsYjUYEN",
    "9": "https://square.link/u/2QrMVDp9",
    "10": "https://square.link/u/7QQHxDzS"
  },
  "2026-12-12": {
    "1": "https://square.link/u/nuobumeG",
    "2": "https://square.link/u/xzHpd97Q",
    "3": "https://square.link/u/TLlx4VjW",
    "4": "https://square.link/u/j3fddjLo",
    "5": "https://square.link/u/Ft38uZiX",
    "6": "https://square.link/u/bGdr52fL",
    "7": "https://square.link/u/gjfFpdXO",
    "8": "https://square.link/u/kaqEzMS3",
    "9": "https://square.link/u/ybmLHGV1",
    "10": "https://square.link/u/opsHLvBu"
  },
  "2026-12-19": {
    "1": "https://square.link/u/8OWitgvC",
    "2": "https://square.link/u/btHGu9G8",
    "3": "https://square.link/u/JvPB3OUh",
    "4": "https://square.link/u/zzh77D9s",
    "5": "https://square.link/u/e4LxEcdF",
    "6": "https://square.link/u/XuyJgs4t",
    "7": "https://square.link/u/POaLvLBF",
    "8": "https://square.link/u/hDZ0H9WP",
    "9": "https://square.link/u/pSNX7J18",
    "10": "https://square.link/u/NayGiN2c"
  },
  "2026-12-26": {
    "1": "https://square.link/u/wB927Tdz",
    "2": "https://square.link/u/hscsTeks",
    "3": "https://square.link/u/C4gkKWga",
    "4": "https://square.link/u/8nen9OdY",
    "5": "https://square.link/u/FmBYawgn",
    "6": "https://square.link/u/VvHyoAF3",
    "7": "https://square.link/u/AW9FzSFy",
    "8": "https://square.link/u/ouuDkWpm",
    "9": "https://square.link/u/ciEYTraY",
    "10": "https://square.link/u/zRu87EIR"
  },
  "2027-01-02": {
    "1": "https://square.link/u/QAjm2Y9D",
    "2": "https://square.link/u/JN2C94Su",
    "3": "https://square.link/u/Lqbd1Zhy",
    "4": "https://square.link/u/VjIbQchM",
    "5": "https://square.link/u/hkVWUOSE",
    "6": "https://square.link/u/9jD4Zu3C",
    "7": "https://square.link/u/UGod3Pni",
    "8": "https://square.link/u/yeyi61cR",
    "9": "https://square.link/u/dN9QQbAU",
    "10": "https://square.link/u/KmGB4PsU"
  },
  "2027-01-09": {
    "1": "https://square.link/u/jtFIGisP",
    "2": "https://square.link/u/W0WgERlA",
    "3": "https://square.link/u/yoAOPEhR",
    "4": "https://square.link/u/JQ3UvRER",
    "5": "https://square.link/u/clvshzNp",
    "6": "https://square.link/u/A1bvZ7mH",
    "7": "https://square.link/u/GKygRBWc",
    "8": "https://square.link/u/KB4pNlVb",
    "9": "https://square.link/u/z57AoTn4",
    "10": "https://square.link/u/LSKYKpQf"
  },
  "2027-01-16": {
    "1": "https://square.link/u/cBP6ndF0",
    "2": "https://square.link/u/uuOkJkOI",
    "3": "https://square.link/u/ILIAxHBU",
    "4": "https://square.link/u/9RwUoYbH",
    "5": "https://square.link/u/NR1167jN",
    "6": "https://square.link/u/JsjrKfEE",
    "7": "https://square.link/u/Yojnsfo9",
    "8": "https://square.link/u/x0xjqNLZ",
    "9": "https://square.link/u/EMerbHEC",
    "10": "https://square.link/u/v5mm5ORJ"
  },
  "2027-01-23": {
    "1": "https://square.link/u/35uH8iGI",
    "2": "https://square.link/u/Flbs57tR",
    "3": "https://square.link/u/hqQkm1sp",
    "4": "https://square.link/u/jlqzMweG",
    "5": "https://square.link/u/aPzieEVK",
    "6": "https://square.link/u/jTRCz9DR",
    "7": "https://square.link/u/yKJd9LGo",
    "8": "https://square.link/u/E0SJTnsz",
    "9": "https://square.link/u/zCVpbnwY",
    "10": "https://square.link/u/6ff8IDbg"
  },
  "2027-01-30": {
    "1": "https://square.link/u/lMJpsWwh",
    "2": "https://square.link/u/miDGef5h",
    "3": "https://square.link/u/wZwMutBJ",
    "4": "https://square.link/u/GyhIKivl",
    "5": "https://square.link/u/h2XP71y5",
    "6": "https://square.link/u/DtGVK5ZR",
    "7": "https://square.link/u/EIEK5qrm",
    "8": "https://square.link/u/TrmoapqF",
    "9": "https://square.link/u/2LxPR9TI",
    "10": "https://square.link/u/sVrvTDPw"
  },
  "2027-02-06": {
    "1": "https://square.link/u/H7HceFIC",
    "2": "https://square.link/u/0uvzQk46",
    "3": "https://square.link/u/oQmcWtwq",
    "4": "https://square.link/u/0UkMTtpW",
    "5": "https://square.link/u/vVGtKtFP",
    "6": "https://square.link/u/rmhCInnH",
    "7": "https://square.link/u/NXDXpSZC",
    "8": "https://square.link/u/QTwU0IFf",
    "9": "https://square.link/u/5aMiMGFD",
    "10": "https://square.link/u/bQ8eN42V"
  },
  "2027-02-13": {
    "1": "https://square.link/u/jHWwpK77",
    "2": "https://square.link/u/arA8oGvz",
    "3": "https://square.link/u/cXFA1ZFm",
    "4": "https://square.link/u/hqtx40KI",
    "5": "https://square.link/u/CUc3y0Tq",
    "6": "https://square.link/u/8d1FB1g0",
    "7": "https://square.link/u/HgIGmOND",
    "8": "https://square.link/u/lbeeEHKE",
    "9": "https://square.link/u/uz6q0SOp",
    "10": "https://square.link/u/8rWbRFsi"
  },
  "2027-02-20": {
    "1": "https://square.link/u/ISTdErA3",
    "2": "https://square.link/u/CCnfT01V",
    "3": "https://square.link/u/w3GWs1ld",
    "4": "https://square.link/u/LvK9l3WX",
    "5": "https://square.link/u/VjvGcsdK",
    "6": "https://square.link/u/wTLUWcQC",
    "7": "https://square.link/u/shHUtTGU",
    "8": "https://square.link/u/iD8pMYsd",
    "9": "https://square.link/u/L4snKVmE",
    "10": "https://square.link/u/WRc2iMqs"
  },
  "2027-02-27": {
    "1": "https://square.link/u/kgoeWURJ",
    "2": "https://square.link/u/OdnqlZUC",
    "3": "https://square.link/u/QysZ1MVm",
    "4": "https://square.link/u/h7m2lDRa",
    "5": "https://square.link/u/u7T4VfrN",
    "6": "https://square.link/u/PIVjmQm7",
    "7": "https://square.link/u/a6ban8J6",
    "8": "https://square.link/u/IPq0oq5I",
    "9": "https://square.link/u/MvFlnpFG",
    "10": "https://square.link/u/ATbm9PoH"
  },
  "2027-03-06": {
    "1": "https://square.link/u/LPJ73Bpo",
    "2": "https://square.link/u/DUUzX6JY",
    "3": "https://square.link/u/ZWs3uOe2",
    "4": "https://square.link/u/fpTCT4R0",
    "5": "https://square.link/u/Cjuu2W7s",
    "6": "https://square.link/u/VYjWA5bu",
    "7": "https://square.link/u/eTlwvaNz",
    "8": "https://square.link/u/Y0yDZT3v",
    "9": "https://square.link/u/Kcn0i8zf",
    "10": "https://square.link/u/WykbEltp"
  },
  "2027-03-13": {
    "1": "https://square.link/u/CVZttZNR",
    "2": "https://square.link/u/WOBrub5c",
    "3": "https://square.link/u/cKNN1YoK",
    "4": "https://square.link/u/hkVALYrN",
    "5": "https://square.link/u/K6MQsq60",
    "6": "https://square.link/u/xsK4IRRy",
    "7": "https://square.link/u/SMPWxcwE",
    "8": "https://square.link/u/eqCPseNK",
    "9": "https://square.link/u/Lmulrn9W",
    "10": "https://square.link/u/l9yxV9zc"
  },
  "2027-03-20": {
    "1": "https://square.link/u/UlzDc8um",
    "2": "https://square.link/u/kgaxS9W1",
    "3": "https://square.link/u/XHVK9Q6Y",
    "4": "https://square.link/u/eTGYDePT",
    "5": "https://square.link/u/3yGgencT",
    "6": "https://square.link/u/IKq8qeHC",
    "7": "https://square.link/u/RR6KldAe",
    "8": "https://square.link/u/GguK02u3",
    "9": "https://square.link/u/TOOrGAsk",
    "10": "https://square.link/u/i5weZxsV"
  },
  "2027-03-27": {
    "1": "https://square.link/u/8r8g0jR4",
    "2": "https://square.link/u/7YbbLS6B",
    "3": "https://square.link/u/OzyYpvdz",
    "4": "https://square.link/u/qXw9rpiD",
    "5": "https://square.link/u/Y2io5NsD",
    "6": "https://square.link/u/35zcNzvj",
    "7": "https://square.link/u/SFww2fsq",
    "8": "https://square.link/u/fnyGIB6z",
    "9": "https://square.link/u/LdS1B2pH",
    "10": "https://square.link/u/zb4wyYll"
  },
  "2027-04-03": {
    "1": "https://square.link/u/YiDvvG2j",
    "2": "https://square.link/u/kuU4ZB5a",
    "3": "https://square.link/u/i9iOBgt8",
    "4": "https://square.link/u/BxvHwtVF",
    "5": "https://square.link/u/ZDcuO5vM",
    "6": "https://square.link/u/F7scmP5K",
    "7": "https://square.link/u/btAvnY0E",
    "8": "https://square.link/u/7bDcwRjd",
    "9": "https://square.link/u/Zdav2t9q",
    "10": "https://square.link/u/Jt6RAU8V"
  },
  "2027-04-10": {
    "1": "https://square.link/u/pfbDUiLz",
    "2": "https://square.link/u/NEC9cKzh",
    "3": "https://square.link/u/17lsa2mR",
    "4": "https://square.link/u/n1UYQxtW",
    "5": "https://square.link/u/pdDQsvpw",
    "6": "https://square.link/u/lQyz9DAH",
    "7": "https://square.link/u/Ue3UggIY",
    "8": "https://square.link/u/pxD3nF7K",
    "9": "https://square.link/u/EskqplME",
    "10": "https://square.link/u/43Xqrc3h"
  },
  "2027-04-17": {
    "1": "https://square.link/u/J7GwuRFO",
    "2": "https://square.link/u/cV7yODQY",
    "3": "https://square.link/u/5r1FTvPS",
    "4": "https://square.link/u/p8eqTpk7",
    "5": "https://square.link/u/4OlObROH",
    "6": "https://square.link/u/xpfi8Hfi",
    "7": "https://square.link/u/xvbBL0HN",
    "8": "https://square.link/u/m0S16WbY",
    "9": "https://square.link/u/kY5RlbwB",
    "10": "https://square.link/u/C3DAlkDx"
  },
  "2027-04-24": {
    "1": "https://square.link/u/LGX8TCzY",
    "2": "https://square.link/u/cyssMT8l",
    "3": "https://square.link/u/pTeWRF8E",
    "4": "https://square.link/u/3TGmoYMg",
    "5": "https://square.link/u/71imlIme",
    "6": "https://square.link/u/XzZ94y77",
    "7": "https://square.link/u/0iuCh9vl",
    "8": "https://square.link/u/XcqTyi6L",
    "9": "https://square.link/u/HiaitE9p",
    "10": "https://square.link/u/5YgvVJEw"
  },
  "2027-05-01": {
    "1": "https://square.link/u/A9fT5ZWG",
    "2": "https://square.link/u/kKlGdJZz",
    "3": "https://square.link/u/Gh2lVy9N",
    "4": "https://square.link/u/Is24TyeS",
    "5": "https://square.link/u/XDoUo1qg",
    "6": "https://square.link/u/qPSSpTH3",
    "7": "https://square.link/u/sFceR5pJ",
    "8": "https://square.link/u/oLZ90Wkt",
    "9": "https://square.link/u/opRVSZ6P",
    "10": "https://square.link/u/HodnjoqX"
  },
  "2027-05-08": {
    "1": "https://square.link/u/4IZtE3Rq",
    "2": "https://square.link/u/29SB7HLp",
    "3": "https://square.link/u/qfSs7ICp",
    "4": "https://square.link/u/PAPs7yp4",
    "5": "https://square.link/u/KorN7BRu",
    "6": "https://square.link/u/D93lKstP",
    "7": "https://square.link/u/1uIka8bN",
    "8": "https://square.link/u/lggFyf99",
    "9": "https://square.link/u/0UoI4QAi",
    "10": "https://square.link/u/xn3VulxD"
  },
  "2027-05-15": {
    "1": "https://square.link/u/bF8C7awW",
    "2": "https://square.link/u/9i7fXzKB",
    "3": "https://square.link/u/sM5r345F",
    "4": "https://square.link/u/t5Q84iTA",
    "5": "https://square.link/u/IQwD60AC",
    "6": "https://square.link/u/IWDSFXA3",
    "7": "https://square.link/u/dxflMRKl",
    "8": "https://square.link/u/v58nJYcr",
    "9": "https://square.link/u/0pMkO8ST",
    "10": "https://square.link/u/SOkihs84"
  },
  "2027-05-22": {
    "1": "https://square.link/u/ouP7sygd",
    "2": "https://square.link/u/SGKYmTp4",
    "3": "https://square.link/u/AgX7YbBr",
    "4": "https://square.link/u/ska31uPM",
    "5": "https://square.link/u/VHYRZp3r",
    "6": "https://square.link/u/1oj8mhoG",
    "7": "https://square.link/u/rQ8CxwJ8",
    "8": "https://square.link/u/Q5gqoDo1",
    "9": "https://square.link/u/vIipVZ8a",
    "10": "https://square.link/u/LprBkSnL"
  },
  "2027-05-29": {
    "1": "https://square.link/u/9C9GvQ9x",
    "2": "https://square.link/u/xEd411Wp",
    "3": "https://square.link/u/Pj9R2ARi",
    "4": "https://square.link/u/zFeaSttP",
    "5": "https://square.link/u/HfTdDiUL",
    "6": "https://square.link/u/YDLm7X6j",
    "7": "https://square.link/u/bZLuc1Te",
    "8": "https://square.link/u/Q41dUOMb",
    "9": "https://square.link/u/BKusL9ax",
    "10": "https://square.link/u/419eVd7H"
  },
  "2027-06-05": {
    "1": "https://square.link/u/3oPCPQhL",
    "2": "https://square.link/u/L5ooV2zq",
    "3": "https://square.link/u/7yhKGMoR",
    "4": "https://square.link/u/vZbAiGvs",
    "5": "https://square.link/u/cq9mGoNP",
    "6": "https://square.link/u/SPkBTyYo",
    "7": "https://square.link/u/erWOB8rD",
    "8": "https://square.link/u/uRRxlWPD",
    "9": "https://square.link/u/JAiPmTJT",
    "10": "https://square.link/u/U3jJWWKt"
  },
  "2027-06-12": {
    "1": "https://square.link/u/GWiYdIYg",
    "2": "https://square.link/u/I38S3DEi",
    "3": "https://square.link/u/YN4ZIAiE",
    "4": "https://square.link/u/F1QVWXhn",
    "5": "https://square.link/u/4Fle7JS3",
    "6": "https://square.link/u/0phiqClh",
    "7": "https://square.link/u/iDpKWIDq",
    "8": "https://square.link/u/qm3KJ56H",
    "9": "https://square.link/u/t8eUEgDQ",
    "10": "https://square.link/u/iFLxIKTg"
  },
  "2027-06-19": {
    "1": "https://square.link/u/zy5SJ3W8",
    "2": "https://square.link/u/I9NhXHOH",
    "3": "https://square.link/u/ZTK1TMpS",
    "4": "https://square.link/u/BiRaLP9p",
    "5": "https://square.link/u/7DjSP6Vs",
    "6": "https://square.link/u/ecALm3r9",
    "7": "https://square.link/u/48HQYSMO",
    "8": "https://square.link/u/pechTZRd",
    "9": "https://square.link/u/JZJC7ysi",
    "10": "https://square.link/u/3VreJujS"
  },
  "2027-06-26": {
    "1": "https://square.link/u/J6HCHdrK",
    "2": "https://square.link/u/8lf627l3",
    "3": "https://square.link/u/zY3jlnsm",
    "4": "https://square.link/u/1DrVg4Cf",
    "5": "https://square.link/u/HCHMc1Xw",
    "6": "https://square.link/u/4ksmYef3",
    "7": "https://square.link/u/b4Q29xGc",
    "8": "https://square.link/u/xwJLkLIf",
    "9": "https://square.link/u/q33J1pyo",
    "10": "https://square.link/u/asjJiHEg"
  },
  "2027-07-03": {
    "1": "https://square.link/u/kM8mX0KO",
    "2": "https://square.link/u/50jn91Nd",
    "3": "https://square.link/u/wUs7T889",
    "4": "https://square.link/u/xaBcvLC7",
    "5": "https://square.link/u/bvFtzIui",
    "6": "https://square.link/u/y8ak1OSy",
    "7": "https://square.link/u/5MrbG9Lv",
    "8": "https://square.link/u/vcigSSsr",
    "9": "https://square.link/u/Xf8uX3XX",
    "10": "https://square.link/u/BXQzsIvH"
  },
  "2027-07-10": {
    "1": "https://square.link/u/1K7hIQjQ",
    "2": "https://square.link/u/GrssSF8N",
    "3": "https://square.link/u/Ddy3ouA1",
    "4": "https://square.link/u/VTKvTj5N",
    "5": "https://square.link/u/uBjNCqD7",
    "6": "https://square.link/u/coSJ3qK9",
    "7": "https://square.link/u/YknHZaaJ",
    "8": "https://square.link/u/RQp2ILb9",
    "9": "https://square.link/u/3qxY5ctx",
    "10": "https://square.link/u/Gdbi7Z9R"
  },
  "2027-07-17": {
    "1": "https://square.link/u/yyEJ5bv0",
    "2": "https://square.link/u/BeXlTa3y",
    "3": "https://square.link/u/lOibdlTi",
    "4": "https://square.link/u/U57GocGl",
    "5": "https://square.link/u/iirjZi3f",
    "6": "https://square.link/u/7a4e6u14",
    "7": "https://square.link/u/SXAXNSN2",
    "8": "https://square.link/u/waSA91cK",
    "9": "https://square.link/u/VOKcVIKu",
    "10": "https://square.link/u/U0RqpI3v"
  }
}